_fristenkalender_generator_version.py
fristenkalender_generator/__init__.py
fristenkalender_generator/bdew_calendar_generator.py
fristenkalender_generator/py.typed
fristenkalender_generator/utils.py
fristenkalender_generator-1.0.3.dist-info/METADATA
fristenkalender_generator-1.0.3.dist-info/WHEEL
fristenkalender_generator-1.0.3.dist-info/licenses/LICENSE
fristenkalender_generator-1.0.3.dist-info/RECORD
