Metadata-Version: 2.4
Name: fristenkalender_generator
Version: 1.0.3
Summary: A Python package that generates the raw data for the 'Hochfrequenz Fristenkalender'
Project-URL: Changelog, https://github.com/Hochfrequenz/fristenkalender_generator/releases
Project-URL: Homepage, https://github.com/Hochfrequenz/fristenkalender_generator
Author-email: Konstantin Klein <konstantin.klein@hochfrequenz.de>
License: MIT
License-File: LICENSE
Keywords: bdew,fristenkalender,hochfrequenz
Classifier: Development Status :: 4 - Beta
Classifier: Environment :: Console
Classifier: Intended Audience :: Developers
Classifier: License :: OSI Approved :: MIT License
Classifier: Operating System :: OS Independent
Classifier: Programming Language :: Python
Classifier: Programming Language :: Python :: 3 :: Only
Classifier: Programming Language :: Python :: 3.9
Classifier: Programming Language :: Python :: 3.10
Classifier: Programming Language :: Python :: 3.11
Classifier: Programming Language :: Python :: 3.12
Classifier: Programming Language :: Python :: 3.13
Classifier: Programming Language :: Python :: 3.14
Requires-Python: >=3.9
Requires-Dist: bdew-datetimes>=0.9.1
Requires-Dist: holidays>=0.78
Requires-Dist: icalendar
Provides-Extra: coverage
Requires-Dist: coverage==7.13.1; extra == 'coverage'
Provides-Extra: dev
Requires-Dist: pip-tools; extra == 'dev'
Provides-Extra: formatting
Requires-Dist: black==25.12.0; extra == 'formatting'
Requires-Dist: isort==7.0.0; extra == 'formatting'
Provides-Extra: linting
Requires-Dist: pylint==4.0.4; extra == 'linting'
Provides-Extra: packaging
Requires-Dist: build==1.3.0; extra == 'packaging'
Requires-Dist: twine==6.2.0; extra == 'packaging'
Provides-Extra: spell-check
Requires-Dist: codespell==2.4.1; extra == 'spell-check'
Provides-Extra: tests
Requires-Dist: pytest==9.0.2; extra == 'tests'
Requires-Dist: syrupy==5.0.0; extra == 'tests'
Provides-Extra: type-check
Requires-Dist: mypy==1.19.1; extra == 'type-check'
